lightningtoolkit/__init__.py
lightningtoolkit/run.py
lightningtoolkit-1.0.4.dist-info/LICENSE
lightningtoolkit-1.0.4.dist-info/METADATA
lightningtoolkit-1.0.4.dist-info/WHEEL
lightningtoolkit-1.0.4.dist-info/top_level.txt
lightningtoolkit-1.0.4.dist-info/RECORD
